README.md
setup.cfg
setup.py
amino.sf.egg-info/PKG-INFO
amino.sf.egg-info/SOURCES.txt
amino.sf.egg-info/dependency_links.txt
amino.sf.egg-info/requires.txt
amino.sf.egg-info/top_level.txt
amino_sf/__init__.py
amino_sf/acm.py
amino_sf/client.py
amino_sf/socket.py
amino_sf/sub_client.py
amino_sf/asynco/__init__.py
amino_sf/asynco/acm.py
amino_sf/asynco/client.py
amino_sf/asynco/socket.py
amino_sf/asynco/sub_client.py
amino_sf/lib/__init__.py
amino_sf/lib/util/__init__.py
amino_sf/lib/util/device.py
amino_sf/lib/util/exceptions.py
amino_sf/lib/util/headers.py
amino_sf/lib/util/helpers.py
amino_sf/lib/util/objects.py