Metadata-Version: 1.2
Name: amino.sf
Version: 1.0
Summary: Library for Amino. Telegram- https://t.me/spi22der
Home-page: UNKNOWN
Author: sfah
License: MIT
Keywords: aminoapps,amino.sf,amino,amino-bot,narvii,api,python,python3,python3.x,sfah
Platform: UNKNOWN
Requires-Python: >=3.6
